{
	"name": "Runtime.Web",
	"assets":
	[
		"App.bay",
		"AppHook.bay",
		"BaseRoute.bay",
		"Component.bay",
		"Cookie.bay",
		"Layout.bay",
		"Listener.bay",
		"LocaleModel.bay",
		"Message.bay",
		"RenderContainer.bay",
		"RenderProvider.es6",
		"Request.bay",
		"Response.bay",
		"Route.bay",
		"RouteInfo.bay",
		"RouteList.bay",
		"SeoModel.bay",
		"VirtualDom.bay",
		"Events/BaseEvent.bay",
		"Events/WebEvent.bay",
		"Events/BlurEvent.bay",
		"Events/ChangeEvent.bay",
		"Events/CommitModelEvent.bay",
		"Events/FocusEvent.bay",
		"Events/KeyboardEvent.bay",
		"Events/KeyDownEvent.bay",
		"Events/KeyPressEvent.bay",
		"Events/KeyUpEvent.bay",
		"Events/MouseEvent.bay",
		"Events/MouseClickEvent.bay",
		"Events/MouseContextMenuEvent.bay",
		"Events/MouseDoubleClickEvent.bay",
		"Events/MouseDownEvent.bay",
		"Events/MouseEnterEvent.bay",
		"Events/MouseLeaveEvent.bay",
		"Events/MouseMoveEvent.bay",
		"Events/MouseOutEvent.bay",
		"Events/MouseOverEvent.bay",
		"Events/MouseUpEvent.bay",
		"Events/MouseWheelEvent.bay",
		"Events/SignalEvent.bay",
		"ModuleDescription.bay"
	],
	"src": "./bay",
	"dest":
	{
		"php": "./php",
		"es6": "./es6"
	},
	"whitelist":
	[
		"\\.bay$",
		"\\.php$",
		"\\.js$"
	]
}